transmitm/__init__.py
transmitm/proxy.py
transmitm/tcp.py
transmitm/transmitm.py
transmitm/udp.py
transmitm/__pycache__/__init__.cpython-36.pyc
transmitm/__pycache__/__init__.cpython-37.pyc
transmitm/__pycache__/proxy.cpython-36.pyc
transmitm/__pycache__/proxy.cpython-37.pyc
transmitm/__pycache__/tcp.cpython-36.pyc
transmitm/__pycache__/tcp.cpython-37.pyc
transmitm/__pycache__/transmitm.cpython-36.pyc
transmitm/__pycache__/transmitm.cpython-37.pyc
transmitm/__pycache__/udp.cpython-36.pyc
transmitm/__pycache__/udp.cpython-37.pyc
transmitm-0.1.0.dist-info/METADATA
transmitm-0.1.0.dist-info/WHEEL
transmitm-0.1.0.dist-info/top_level.txt
transmitm-0.1.0.dist-info/RECORD
