Metadata-Version: 2.1
Name: transmitm
Version: 0.1.0
Summary: Transport layer transparent intercepting proxy.
Home-page: https://github.com/tsundokul/transmitm
Author: Daniel Timofte @tim17d
Author-email: timofte.daniel@tuta.io
License: MIT License
Keywords: transparent mitm man-in-the-middle proxy
Platform: UNKNOWN
Classifier: Development Status :: 4 - Beta
Classifier: Topic :: System :: Networking
Classifier: Topic :: System :: Networking :: Monitoring
Classifier: Topic :: Security
Classifier: Operating System :: POSIX :: Linux
Classifier: Operating System :: Microsoft :: Windows
Classifier: License :: OSI Approved :: MIT License
Classifier: Programming Language :: Python :: 3
Requires-Python: >=3.5
Requires-Dist: twisted (>=20.3)
